<?xml version="1.0" encoding="latin1"?>
<EXTENSION VERSION="20.1">
<LOGICS>
<LOGICITEM NAME="Extents">
	<STATE NAME="Chart2dViewerExtentsState" VERSION="20.1">
	<PROPERTIES>
	<PROPERTY NAME="XAxisMin">
	<VALUE>-2.</VALUE>
	</PROPERTY>
	<PROPERTY NAME="XAxisMax">
	<VALUE>5.57132385237017</VALUE>
	</PROPERTY>
	<PROPERTY NAME="YAxisMin">
	<VALUE>-1839.722508563713</VALUE>
	</PROPERTY>
	<PROPERTY NAME="YAxisMax">
	<VALUE>-1839.4351282897</VALUE>
	</PROPERTY>
	</PROPERTIES>
	</STATE>
</LOGICITEM>
</LOGICS>
</EXTENSION>
